HISTORY.md
MANIFEST.in
README.md
setup.cfg
setup.py
versioneer.py
rqsdk/__init__.py
rqsdk/__main__.py
rqsdk/_version.py
rqsdk/cmds.py
rqsdk/const.py
rqsdk/license_helper.py
rqsdk/proxy_helper.py
rqsdk/script_update.py
rqsdk/testing.py
rqsdk.egg-info/PKG-INFO
rqsdk.egg-info/SOURCES.txt
rqsdk.egg-info/dependency_links.txt
rqsdk.egg-info/entry_points.txt
rqsdk.egg-info/not-zip-safe
rqsdk.egg-info/requires.txt
rqsdk.egg-info/top_level.txt